bodewell_ui_py/__init__.py
bodewell_ui_py/bodewell_theme.py
bodewell_ui_py-0.1.0.dist-info/METADATA
bodewell_ui_py-0.1.0.dist-info/WHEEL
bodewell_ui_py-0.1.0.dist-info/top_level.txt
bodewell_ui_py-0.1.0.dist-info/RECORD
