Metadata-Version: 2.4
Name: bodewell-ui-py
Version: 0.1.0
Summary: A themed component library for building Bodewell apps with Python and Dash.
Home-page: https://github.com/bodewell-io/bodewell-ui-py
Author: Bodewell
Author-email: contact@bodewell.io
Classifier: Programming Language :: Python :: 3
Classifier: License :: OSI Approved :: MIT License
Classifier: Operating System :: OS Independent
Requires-Python: >=3.6
Requires-Dist: dash>=2.0.0
Requires-Dist: dash-mantine-components>=0.12.1
Dynamic: author
Dynamic: author-email
Dynamic: classifier
Dynamic: description
Dynamic: description-content-type
Dynamic: home-page
Dynamic: requires-dist
Dynamic: requires-python
Dynamic: summary
